quantcompare/__init__.py
quantcompare/main.py
quantcompare-0.0.2.dist-info/METADATA
quantcompare-0.0.2.dist-info/WHEEL
quantcompare-0.0.2.dist-info/entry_points.txt
quantcompare-0.0.2.dist-info/top_level.txt
quantcompare-0.0.2.dist-info/RECORD
