Metadata-Version: 2.1
Name: quantcompare
Version: 0.0.2
Summary: Simple tool to compare sage quant results!
Author-email: Patrick Garrett <pgarrett@scripps.edu>
Classifier: Programming Language :: Python :: 3
Classifier: Development Status :: 4 - Beta
Classifier: License :: OSI Approved :: MIT License
Classifier: Operating System :: OS Independent
Requires-Python: >=3.9
Requires-Dist: pandas
Requires-Dist: argparse
Requires-Dist: numpy
Requires-Dist: tqdm
Requires-Dist: scipy
Requires-Dist: statsmodels
Requires-Dist: setuptools
Requires-Dist: pyarrow
